aws_nuke_exporter/__init__.py
aws_nuke_exporter/exceptions.py
aws_nuke_exporter/exporter.py
aws_nuke_exporter/json_logger.py
tests/__init__.py
tests/test_exporter.py
tests/test_json_logger.py
tests/test_version.py
aws_nuke_exporter-1.0.4.dist-info/LICENSE
aws_nuke_exporter-1.0.4.dist-info/METADATA
aws_nuke_exporter-1.0.4.dist-info/WHEEL
aws_nuke_exporter-1.0.4.dist-info/entry_points.txt
aws_nuke_exporter-1.0.4.dist-info/top_level.txt
aws_nuke_exporter-1.0.4.dist-info/RECORD
