Metadata-Version: 2.1
Name: aws-nuke-exporter
Version: 1.0.4
Summary: A tool for exporting aws-nuke logs in JSON or CSV formats.
Home-page: https://github.com/oijkn/aws-nuke-exporter
Author: oijkn
Author-email: peacefull64@hotmail.fr
License: GPL
Classifier: Programming Language :: Python :: 3
Classifier: License :: OSI Approved :: GNU General Public License (GPL)
Classifier: Operating System :: OS Independent
Requires-Python: >=3.6
License-File: LICENSE
